windflow_leo/__init__.py
windflow_leo/cld_mask_cth.py
windflow_leo/output.py
windflow_leo/plot.py
windflow_leo/polar_RAFT_runner.py
windflow_leo/raft_inference.py
windflow_leo/resample.py
windflow_leo-0.2.2.dist-info/METADATA
windflow_leo-0.2.2.dist-info/WHEEL
windflow_leo-0.2.2.dist-info/licenses/LICENSE
windflow_leo-0.2.2.dist-info/RECORD
