Metadata-Version: 2.3
Name: windflow_leo
Version: 0.2.2
Summary: Optical Flow derived winds from overlapping LEO granules
Project-URL: Homepage, https://gitlab.ssec.wisc.edu/rink/windflow_leo
Author-email: "T.Rink" <rink@ssec.wisc.edu>
License-File: LICENSE
Classifier: License :: OSI Approved :: MIT License
Classifier: Operating System :: OS Independent
Classifier: Programming Language :: Python :: 3
Requires-Python: >=3.8
Requires-Dist: boto3
Requires-Dist: botocore
Requires-Dist: cartopy
Requires-Dist: dask
Requires-Dist: h5py
Requires-Dist: largestinteriorrectangle
Requires-Dist: matplotlib
Requires-Dist: metpy
Requires-Dist: netcdf4
Requires-Dist: numpy
Requires-Dist: pandas
Requires-Dist: pillow
Requires-Dist: pyproj
Requires-Dist: pyresample
Requires-Dist: scipy
Requires-Dist: torch
Requires-Dist: torchvision
Requires-Dist: xarray
